---
sidebar_position: 1
title: "字节码"
description: "Java字节码结构与指令集"
authors: [Laby]
last_update:
  date: 2025-08-07
  author: Laby
---

# 字节码

## 字节码结构

### Class文件结构

Java字节码文件(.class)的结构如下：

```java
ClassFile {
    u4             magic;              // 魔数：0xCAFEBABE
    u2             minor_version;      // 次版本号
    u2             major_version;      // 主版本号
    u2             constant_pool_count; // 常量池数量
    cp_info        constant_pool[constant_pool_count-1]; // 常量池
    u2             access_flags;       // 访问标志
    u2             this_class;         // 当前类索引
    u2             super_class;        // 父类索引
    u2             interfaces_count;    // 接口数量
    u2             interfaces[interfaces_count]; // 接口索引数组
    u2             fields_count;       // 字段数量
    field_info     fields[fields_count]; // 字段表
    u2             methods_count;      // 方法数量
    method_info    methods[methods_count]; // 方法表
    u2             attributes_count;   // 属性数量
    attribute_info attributes[attributes_count]; // 属性表
}
```

### 魔数 (Magic Number)

```java
// 魔数：0xCAFEBABE
// 用于识别文件是否为有效的Class文件
public class MagicNumber {
    public static void main(String[] args) {
        // 0xCAFEBABE = -889275714
        System.out.println(0xCAFEBABE);
    }
}
```

### 版本号

```java
// 版本号对应关系
Java 8:  0x34 (52)
Java 9:  0x35 (53)
Java 10: 0x36 (54)
Java 11: 0x37 (55)
Java 12: 0x38 (56)
Java 13: 0x39 (57)
Java 14: 0x3A (58)
Java 15: 0x3B (59)
Java 16: 0x3C (60)
Java 17: 0x3D (61)
Java 18: 0x3E (62)
Java 19: 0x3F (63)
Java 20: 0x40 (64)
Java 21: 0x41 (65)
```

## 常量池

### 常量池类型

```java
// 常量池类型表
CONSTANT_Class              = 7;   // 类或接口的符号引用
CONSTANT_Fieldref          = 9;   // 字段的符号引用
CONSTANT_Methodref         = 10;  // 方法的符号引用
CONSTANT_InterfaceMethodref = 11; // 接口方法的符号引用
CONSTANT_String            = 8;   // 字符串字面量
CONSTANT_Integer           = 3;   // 整型字面量
CONSTANT_Float             = 4;   // 浮点型字面量
CONSTANT_Long              = 5;   // 长整型字面量
CONSTANT_Double            = 6;   // 双精度浮点型字面量
CONSTANT_NameAndType       = 12;  // 字段或方法的部分符号引用
CONSTANT_Utf8              = 1;   // UTF-8编码的字符串
CONSTANT_MethodHandle      = 15;  // 方法句柄
CONSTANT_MethodType        = 16;  // 方法类型
CONSTANT_InvokeDynamic     = 18;  // 动态方法调用点
```

### 常量池示例

```java
public class ConstantPoolExample {
    public static final String CONSTANT_STRING = "Hello World";
    public static final int CONSTANT_INT = 100;
    
    public void method() {
        String localString = "Local String";
        int localInt = 200;
    }
}
```

对应的常量池：

```java
// 常量池内容
#1 = Class              #2              // ConstantPoolExample
#2 = Utf8               ConstantPoolExample
#3 = Class              #4              // java/lang/Object
#4 = Utf8               java/lang/Object
#5 = Utf8               CONSTANT_STRING
#6 = Utf8               Ljava/lang/String;
#7 = Utf8               CONSTANT_INT
#8 = Utf8               I
#9 = String             #10             // Hello World
#10 = Utf8              Hello World
#11 = Integer           100
#12 = Utf8              method
#13 = Utf8              ()V
#14 = Utf8              Local String
#15 = String            #14             // Local String
#16 = Integer           200
```

## 访问标志

### 访问标志位

```java
// 访问标志位定义
ACC_PUBLIC       = 0x0001; // public
ACC_PRIVATE      = 0x0002; // private
ACC_PROTECTED    = 0x0004; // protected
ACC_STATIC       = 0x0008; // static
ACC_FINAL        = 0x0010; // final
ACC_SUPER        = 0x0020; // 使用新的invokespecial语义
ACC_SYNCHRONIZED = 0x0020; // synchronized
ACC_VOLATILE     = 0x0040; // volatile
ACC_TRANSIENT    = 0x0080; // transient
ACC_NATIVE       = 0x0100; // native
ACC_INTERFACE    = 0x0200; // interface
ACC_ABSTRACT     = 0x0400; // abstract
ACC_STRICT       = 0x0800; // strictfp
ACC_SYNTHETIC    = 0x1000; // 合成
ACC_ANNOTATION   = 0x2000; // annotation
ACC_ENUM         = 0x4000; // enum
```

### 访问标志示例

```java
// 访问标志示例
public class AccessFlagsExample {
    public static final String PUBLIC_STATIC_FINAL = "test";
    private volatile int privateVolatileField;
    
    public synchronized void publicSynchronizedMethod() {}
    private native void privateNativeMethod();
    protected abstract void protectedAbstractMethod();
}
```

## 字节码指令

### 加载和存储指令

```java
// 加载指令
iload_0      // 加载第0个int型局部变量
iload_1      // 加载第1个int型局部变量
aload_0      // 加载第0个引用型局部变量
aload_1      // 加载第1个引用型局部变量
lload_0      // 加载第0个long型局部变量
fload_0      // 加载第0个float型局部变量
dload_0      // 加载第0个double型局部变量

// 存储指令
istore_0     // 将int型数值存入第0个局部变量
astore_0     // 将引用型数值存入第0个局部变量
lstore_0     // 将long型数值存入第0个局部变量
fstore_0     // 将float型数值存入第0个局部变量
dstore_0     // 将double型数值存入第0个局部变量
```

### 运算指令

```java
// 算术运算指令
iadd         // int型加法
isub         // int型减法
imul         // int型乘法
idiv         // int型除法
irem         // int型取余
ineg         // int型取负

// 位运算指令
ishl         // int型左移
ishr         // int型算术右移
iushr        // int型逻辑右移
iand         // int型按位与
ior          // int型按位或
ixor         // int型按位异或
```

### 类型转换指令

```java
// 类型转换指令
i2l          // int转long
i2f          // int转float
i2d          // int转double
l2i          // long转int
l2f          // long转float
l2d          // long转double
f2i          // float转int
f2l          // float转long
f2d          // float转double
d2i          // double转int
d2l          // double转long
d2f          // double转float
i2b          // int转byte
i2c          // int转char
i2s          // int转short
```

### 对象操作指令

```java
// 对象操作指令
new          // 创建对象
newarray     // 创建基本类型数组
anewarray    // 创建引用类型数组
arraylength  // 获取数组长度
getfield     // 获取对象字段
putfield     // 设置对象字段
getstatic    // 获取静态字段
putstatic    // 设置静态字段
```

### 方法调用指令

```java
// 方法调用指令
invokevirtual    // 调用实例方法
invokespecial    // 调用特殊方法（构造方法、私有方法、父类方法）
invokestatic     // 调用静态方法
invokeinterface  // 调用接口方法
invokedynamic    // 调用动态方法
```

### 控制转移指令

```java
// 条件分支指令
ifeq         // 当栈顶int型数值等于0时跳转
ifne         // 当栈顶int型数值不等于0时跳转
iflt         // 当栈顶int型数值小于0时跳转
ifle         // 当栈顶int型数值小于等于0时跳转
ifgt         // 当栈顶int型数值大于0时跳转
ifge         // 当栈顶int型数值大于等于0时跳转

// 比较分支指令
if_icmpeq    // 比较栈顶两int型数值大小，当结果等于0时跳转
if_icmpne    // 比较栈顶两int型数值大小，当结果不等于0时跳转
if_icmplt    // 比较栈顶两int型数值大小，当结果小于0时跳转
if_icmple    // 比较栈顶两int型数值大小，当结果小于等于0时跳转
if_icmpgt    // 比较栈顶两int型数值大小，当结果大于0时跳转
if_icmpge    // 比较栈顶两int型数值大小，当结果大于等于0时跳转

// 无条件分支指令
goto         // 无条件跳转
jsr          // 跳转到指定16位offset位置，并将jsr下一条指令地址压入栈顶
ret          // 返回至本地变量指定的index的指令位置
```

## 字节码示例

### 简单方法字节码

```java
public class BytecodeExample {
    public int add(int a, int b) {
        return a + b;
    }
}
```

对应的字节码：

```java
// 方法字节码
public int add(int, int);
  Code:
   0: iload_1        // 加载参数a
   1: iload_2        // 加载参数b
   2: iadd           // 执行加法
   3: ireturn        // 返回结果
```

### 循环字节码

```java
public class LoopExample {
    public void loop() {
        for (int i = 0; i < 10; i++) {
            System.out.println(i);
        }
    }
}
```

对应的字节码：

```java
// 循环字节码
public void loop();
  Code:
   0: iconst_0       // 将0压入栈顶
   1: istore_1       // 将0存入局部变量i
   2: iload_1        // 加载i
   3: bipush 10      // 将10压入栈顶
   5: if_icmpge 21   // 如果i>=10，跳转到21
   8: getstatic #2   // 获取System.out
   11: iload_1       // 加载i
   12: invokevirtual #3 // 调用println方法
   15: iinc 1, 1     // i++
   18: goto 2        // 跳转到2
   21: return        // 返回
```

### 异常处理字节码

```java
public class ExceptionExample {
    public void exception() {
        try {
            int result = 1 / 0;
        } catch (ArithmeticException e) {
            System.out.println("除零异常");
        }
    }
}
```

对应的字节码：

```java
// 异常处理字节码
public void exception();
  Code:
   0: iconst_1       // 将1压入栈顶
   1: iconst_0       // 将0压入栈顶
   2: idiv           // 执行除法
   3: istore_1       // 存储结果
   4: goto 12        // 跳转到12
   7: astore_1       // 存储异常对象
   8: getstatic #2   // 获取System.out
   11: invokevirtual #3 // 调用println方法
   12: return        // 返回
  Exception table:
   from    to  target type
       0     4     7   Class java/lang/ArithmeticException
```

## 反编译工具

### javap命令

```bash
# 查看类文件的基本信息
javap -verbose BytecodeExample.class

# 查看方法字节码
javap -c BytecodeExample.class

# 查看常量池
javap -constants BytecodeExample.class
```

### 第三方工具

```bash
# CFR反编译器
java -jar cfr.jar BytecodeExample.class

# Procyon反编译器
java -jar procyon-decompiler.jar BytecodeExample.class

# Fernflower反编译器
java -jar fernflower.jar BytecodeExample.class
```

### IDE插件

```java
// IntelliJ IDEA
// 内置字节码查看器：View -> Show Bytecode

// Eclipse
// 安装Bytecode Outline插件
```

## 字节码优化

### 编译时优化

```java
// 常量折叠
public class ConstantFolding {
    public static final int CONSTANT = 1 + 2; // 编译时计算为3
    
    public int method() {
        return 10 * 20; // 编译时计算为200
    }
}
```

### 运行时优化

```java
// JIT编译优化
public class JITOptimization {
    public void hotMethod() {
        // 热点代码会被JIT编译为机器码
        for (int i = 0; i < 10000; i++) {
            // 频繁执行的代码
        }
    }
}
```

## 面试题

### 1. 什么是字节码？

字节码是Java源代码编译后的中间表示形式，是JVM能够理解和执行的指令集。

### 2. Class文件的结构？

- **魔数**：0xCAFEBABE，用于识别Class文件
- **版本号**：主版本号和次版本号
- **常量池**：存储字面量和符号引用
- **访问标志**：类的访问修饰符
- **类索引、父类索引、接口索引**
- **字段表、方法表、属性表**

### 3. 常量池的作用？

常量池存储编译期生成的各种字面量和符号引用，包括：
- 类和接口的全限定名
- 字段的名称和描述符
- 方法的名称和描述符
- 字符串字面量
- 数值字面量

### 4. 字节码指令的分类？

- **加载和存储指令**：在局部变量表和操作数栈之间传输数据
- **运算指令**：对操作数栈上的值进行运算
- **类型转换指令**：将一种数值类型转换为另一种
- **对象操作指令**：创建对象、访问对象字段等
- **方法调用指令**：调用方法
- **控制转移指令**：条件分支、无条件跳转等
- **异常处理指令**：抛出异常

### 5. 如何查看字节码？

使用javap命令：
```bash
javap -verbose ClassName.class
```

### 6. 字节码优化的方式？

- **编译时优化**：常量折叠、死代码消除等
- **运行时优化**：JIT编译、内联优化等

### 7. 字节码与机器码的区别？

- **字节码**：平台无关的中间表示
- **机器码**：特定平台的本地代码

### 8. 为什么Java需要字节码？

- **平台无关性**：一次编译，到处运行
- **安全性**：字节码验证确保安全性
- **优化空间**：JVM可以进行运行时优化

### 9. 字节码指令的执行过程？

1. **取指令**：从字节码数组中取出指令
2. **解码**：解析指令的操作码和操作数
3. **执行**：执行指令对应的操作
4. **更新PC**：更新程序计数器

### 10. 如何分析字节码性能？

- 使用JProfiler等工具分析热点方法
- 查看JIT编译日志
- 分析字节码指令的执行频率 